free_range_exercises/chapter-4/ch4-2/chapter_4-2.vhd
-- Libraries
library ieee;
use ieee.std_logic_1164.all;

-- Chapter 4 - Example 2
-- Write the VHDL code to implement the function  
-- expressed by the following logic equation: 
-- F3 = L' * M' * N + L * M
-- F3 = (L' AND M' AND N') OR (L AND M)

entity equation_f3 is
    port (
        input_L : in std_logic;
        input_M : in std_logic;
        input_N : in std_logic;
        output_F3 : out std_logic
    );
end entity;

architecture rtl of equation_f3 is
begin
   output_F3 <= (not(input_L) and not(input_M) and input_N) or (input_L and input_M) ;
end architecture;

-- See alternative solution that uses intermediate signals
-- Alternative solution is more closer to what the discrete gates look like

free_range_exercises/chapter-4/ch4-2/equationf3_test.vhd
library ieee;
use ieee.std_logic_1164.all;

entity equation_f3_test_bench is
    -- No ports in a test bench
end equation_f3_test_bench;

architecture test of equation_f3_test_bench is 
    component equation_f3
        port (
            input_L : in std_logic;
            input_M : in std_logic;
            input_N : in std_logic;
            output_F3 : out std_logic
        );
    end component equation_f3;

    signal input_L, input_M, input_N, output_F3 : std_logic;
begin

    equationf3 : equation_f3
    port map (
        input_L => input_L,
        input_M => input_M,
        input_N => input_N,
        output_F3 => output_F3
    );
    
    process begin

        -- Test case X
        -- No Value
        input_L <= 'X';
        input_M <= 'X';
        input_N <= 'X';
        wait for 1 ns;

        -- Test case 0
        -- ( 0 * 0 * 0 )'
        input_L <= '0';
        input_M <= '0';
        input_N <= '0';
        wait for 1 ns;

        -- Test case 1
        -- ( 0 * 0 * 1 )'
        input_L <= '1';
        input_M <= '0';
        input_N <= '0';
        wait for 1 ns;

        -- Test case 2
        -- ( 0 * 1 * 0 )'
        input_L <= '0';
        input_M <= '1';
        input_N <= '0';
        wait for 1 ns;

        -- Test case 3
        -- ( 0 * 1 * 1 )'
        input_L <= '1';
        input_M <= '1';
        input_N <= '0';
        wait for 1 ns;

        -- Test case 4
        -- ( 1 * 0 * 0 )'
        input_L <= '0';
        input_M <= '0';
        input_N <= '1';
        wait for 1 ns;

        -- Test case 5
        -- ( 1 * 0 * 1 )'
        input_L <= '1';
        input_M <= '0';
        input_N <= '1';
        wait for 1 ns;

        -- Test case 6
        -- ( 1 * 1 * 0 )'
        input_L <= '0';
        input_M <= '1';
        input_N <= '1';
        wait for 1 ns;

        -- Test case 7
        -- ( 1 * 1 * 1 )'
        input_L <= '1';
        input_M <= '1';
        input_N <= '1';
        wait for 1 ns;

        -- End simulation
        wait;

        -- Log
        assert false report "Executed Testbench";

        -- End simulation
        wait;
    end process;
end test;

free_range_exercises/chapter-4/ch4-2/equationf3.vcd
$date
  Tue Sep 09 10:24:55 2025
$end
$version
  GHDL v0
$end
$timescale
  1 fs
$end
$scope module standard $end
$upscope $end
$scope module std_logic_1164 $end
$upscope $end
$scope module equation_f3_test_bench $end
$var reg 1 ! input_l $end
$var reg 1 " input_m $end
$var reg 1 # input_n $end
$var reg 1 $ output_f3 $end
$scope module equationf3 $end
$var reg 1 % input_l $end
$var reg 1 & input_m $end
$var reg 1 ' input_n $end
$var reg 1 ( output_f3 $end
$upscope $end
$upscope $end
$enddefinitions $end
#0
X!
X"
X#
X$
X%
X&
X'
X(
#1000000
0!
0"
0#
0$
0%
0&
0'
0(
#2000000
1!
1%
#3000000
0!
1"
0%
1&
#4000000
1!
1$
1%
1(
#5000000
0!
0"
1#
0%
0&
1'
#6000000
1!
0$
1%
0(
#7000000
0!
1"
0%
1&
#8000000
1!
1$
1%
1(
